elasticsearch_rebalancer/__init__.py
elasticsearch_rebalancer/__main__.py
elasticsearch_rebalancer/util.py
elasticsearch_rebalancer-0.6.dist-info/LICENSE.md
elasticsearch_rebalancer-0.6.dist-info/METADATA
elasticsearch_rebalancer-0.6.dist-info/WHEEL
elasticsearch_rebalancer-0.6.dist-info/entry_points.txt
elasticsearch_rebalancer-0.6.dist-info/top_level.txt
elasticsearch_rebalancer-0.6.dist-info/RECORD
